bftools/__init__.py
bftools/compiler.py
bftools/core.py
bftools/decoder.py
bftools/encoder.py
bftools/enums.py
bftools/exceptions.py
bftools/tools.py
bftools-0.4.0.dist-info/LICENSE
bftools-0.4.0.dist-info/METADATA
bftools-0.4.0.dist-info/WHEEL
bftools-0.4.0.dist-info/top_level.txt
bftools-0.4.0.dist-info/RECORD
