Metadata-Version: 2.1
Name: bftools
Version: 0.4.0
Summary: A brainfuck toolbox for python.
Home-page: https://github.com/BobDotCom/bftools
Download-URL: https://github.com/BobDotCom/bftools/releases
Author: BobDotCom
Author-email: bobdotcomgt@gmail.com
License: MIT
Project-URL: Documentation, https://bftools.readthedocs.io/en/latest/index.html
Project-URL: Source, https://github.com/BobDotCom/bftools
Project-URL: Tracker, https://github.com/BobDotCom/bftools/issues
Classifier: Programming Language :: Python :: 3
Classifier: License :: OSI Approved :: MIT License
Classifier: Operating System :: OS Independent
Requires-Python: >=3.6
License-File: LICENSE
Provides-Extra: docs
Requires-Dist: sphinx (==4.3.0) ; extra == 'docs'
Requires-Dist: sphinxcontrib-trio (==1.1.2) ; extra == 'docs'
Requires-Dist: sphinxcontrib-websupport ; extra == 'docs'
Requires-Dist: sphinx-rtd-theme ; extra == 'docs'
Provides-Extra: minify
Requires-Dist: python-minifier (<=2.5) ; extra == 'minify'
